dnora/__init__.py
dnora/converters.py
dnora/file_module.py
dnora/msg.py
dnora/spectral_grid.py
dnora/version.py
dnora/atmosphere/__init__.py
dnora/atmosphere/atmosphere.py
dnora/cacher/__init__.py
dnora/cacher/cache_decorator.py
dnora/cacher/caching_functions.py
dnora/cacher/caching_strategies.py
dnora/cacher/patching_functions.py
dnora/cacher/tiles.py
dnora/current/__init__.py
dnora/current/current.py
dnora/defaults/__init__.py
dnora/defaults/default_reader.py
dnora/defaults/export_defaults.yml
dnora/executer/__init__.py
dnora/executer/decorators.py
dnora/executer/executer.py
dnora/executer/model_runners.py
dnora/executer/post_processors.py
dnora/executer/templates.py
dnora/executer/inputfile/__init__.py
dnora/executer/inputfile/inputfile_writers.py
dnora/executer/inputfile/swan_functions.py
dnora/executer/inputfile/ww3_functions.py
dnora/executer/inputfile/metadata/ww3_bounc/bound.txt
dnora/executer/inputfile/metadata/ww3_bounc/footer.txt
dnora/executer/inputfile/metadata/ww3_bounc/header.txt
dnora/executer/inputfile/metadata/ww3_grid/depth.txt
dnora/executer/inputfile/metadata/ww3_grid/footer.txt
dnora/executer/inputfile/metadata/ww3_grid/grid.txt
dnora/executer/inputfile/metadata/ww3_grid/header.txt
dnora/executer/inputfile/metadata/ww3_grid/inbnd.txt
dnora/executer/inputfile/metadata/ww3_grid/mask.txt
dnora/executer/inputfile/metadata/ww3_grid/rect.txt
dnora/executer/inputfile/metadata/ww3_grid/run.txt
dnora/executer/inputfile/metadata/ww3_grid/spectrum.txt
dnora/executer/inputfile/metadata/ww3_grid/timesteps.txt
dnora/executer/inputfile/metadata/ww3_grid/unst.txt
dnora/executer/inputfile/metadata/ww3_ounf/field.txt
dnora/executer/inputfile/metadata/ww3_ounf/file.txt
dnora/executer/inputfile/metadata/ww3_ounf/footer.txt
dnora/executer/inputfile/metadata/ww3_ounf/header.txt
dnora/executer/inputfile/metadata/ww3_ounp/file.txt
dnora/executer/inputfile/metadata/ww3_ounp/footer.txt
dnora/executer/inputfile/metadata/ww3_ounp/header.txt
dnora-2.4.2.dist-info/licenses/LICENSE
dnora-2.4.2.dist-info/METADATA
dnora-2.4.2.dist-info/WHEEL
dnora-2.4.2.dist-info/top_level.txt
dnora-2.4.2.dist-info/RECORD
