Metadata-Version: 2.4
Name: dnora
Version: 2.4.2
Summary: dnora - a software for dynamical downscaling of wave products
Author-email: Konstantinos Christakos <konstantinosc@met.no>, Jan-Victor Björkqvist <janvb@met.no>
License: MIT License
Project-URL: homepage, https://github.com/MET-OM/dnora
Project-URL: download, https://github.com/MET-OM/dnora
Requires-Python: >=3.9
License-File: LICENSE
Requires-Dist: matplotlib>=3.1
Requires-Dist: numpy>=1.17
Requires-Dist: scipy>=1.7
Requires-Dist: pandas
Requires-Dist: xarray>=0.20.1
Requires-Dist: netCDF4
Requires-Dist: meshio
Requires-Dist: geo-skeletons>=0.21.1
Requires-Dist: geo-parameters>=0.11.0
Requires-Dist: python-dotenv
Requires-Dist: progressbar
Requires-Dist: pyarrow
Requires-Dist: dnplot>=0.4.3
Requires-Dist: dask[dataframe]
Provides-Extra: test
Requires-Dist: pytest>=7.0; extra == "test"
Dynamic: license-file
